mrjob/__init__.py
mrjob/ami.py
mrjob/aws.py
mrjob/bin.py
mrjob/cat.py
mrjob/cloud.py
mrjob/cmd.py
mrjob/compat.py
mrjob/conf.py
mrjob/dataproc.py
mrjob/emr.py
mrjob/hadoop.py
mrjob/iam.py
mrjob/inline.py
mrjob/job.py
mrjob/local.py
mrjob/options.py
mrjob/parse.py
mrjob/pool.py
mrjob/protocol.py
mrjob/py2.py
mrjob/retry.py
mrjob/runner.py
mrjob/setup.py
mrjob/sim.py
mrjob/step.py
mrjob/util.py
mrjob/bootstrap/terminate_idle_cluster_emr.sh
mrjob/examples/__init__.py
mrjob/examples/mr_boom.py
mrjob/examples/mr_count_lines_by_file.py
mrjob/examples/mr_count_lines_right.py
mrjob/examples/mr_count_lines_wrong.py
mrjob/examples/mr_grep.py
mrjob/examples/mr_jar_step_example.py
mrjob/examples/mr_log_sampler.py
mrjob/examples/mr_most_used_word.py
mrjob/examples/mr_next_word_stats.py
mrjob/examples/mr_nick_nack.py
mrjob/examples/mr_nick_nack_input_format.py
mrjob/examples/mr_phone_to_url.py
mrjob/examples/mr_spark_most_used_word.py
mrjob/examples/mr_spark_wordcount.py
mrjob/examples/mr_spark_wordcount_script.py
mrjob/examples/mr_sparkaboom.py
mrjob/examples/mr_text_classifier.py
mrjob/examples/mr_wc.py
mrjob/examples/mr_word_freq_count.py
mrjob/examples/mr_words_containing_u_freq_count.py
mrjob/examples/nicknack-1.0.1.jar
mrjob/examples/spark_wordcount_script.py
mrjob/examples/stop_words.txt
mrjob/examples/docs-to-classify/american_feuillage-whitman-america.txt
mrjob/examples/docs-to-classify/as_i_ponderd_in_silence-whitman.txt
mrjob/examples/docs-to-classify/buckingham_palace-milne-not_america.txt
mrjob/examples/docs-to-classify/chants_democratic-whitman-america.txt
mrjob/examples/docs-to-classify/corner_of_the_street-milne-not_whitman.txt
mrjob/examples/docs-to-classify/happiness-milne.txt
mrjob/examples/docs-to-classify/in_cabind_ships_at_sea-whitman.txt
mrjob/examples/docs-to-classify/lines_and_squares-milne-animals.txt
mrjob/examples/docs-to-classify/ones_self_i_sing-whitman.txt
mrjob/examples/docs-to-classify/puppy_and_i-milne-animals.txt
mrjob-0.7.3.dist-info/LICENSE.txt
mrjob-0.7.3.dist-info/METADATA
mrjob-0.7.3.dist-info/WHEEL
mrjob-0.7.3.dist-info/entry_points.txt
mrjob-0.7.3.dist-info/top_level.txt
mrjob-0.7.3.dist-info/RECORD
