Metadata-Version: 2.1
Name: mrjob
Version: 0.7.3
Summary: Python MapReduce framework
Home-page: http://github.com/Yelp/mrjob
Author: David Marin
Author-email: dm@davidmarin.org
License: Apache
Platform: UNKNOWN
Classifier: Development Status :: 5 - Production/Stable
Classifier: Intended Audience :: Developers
Classifier: License :: OSI Approved :: Apache Software License
Classifier: Natural Language :: English
Classifier: Operating System :: OS Independent
Classifier: Programming Language :: Python
Classifier: Programming Language :: Python :: 2
Classifier: Programming Language :: Python :: 2.7
Classifier: Programming Language :: Python :: 3
Classifier: Programming Language :: Python :: 3.4
Classifier: Programming Language :: Python :: 3.5
Classifier: Programming Language :: Python :: 3.6
Classifier: Programming Language :: Python :: 3.7
Classifier: Topic :: System :: Distributed Computing
Provides: mrjob
Requires-Dist: PyYAML (>=3.10)
Provides-Extra: aws
Requires-Dist: boto3 (>=1.4.6) ; extra == 'aws'
Requires-Dist: botocore (>=1.6.0) ; extra == 'aws'
Provides-Extra: google
Requires-Dist: google-cloud-dataproc (>=0.3.0) ; extra == 'google'
Requires-Dist: google-cloud-logging (>=1.9.0) ; extra == 'google'
Requires-Dist: google-cloud-storage (>=1.13.1) ; extra == 'google'
Provides-Extra: simplejson
Requires-Dist: simplejson ; extra == 'simplejson'
Provides-Extra: ujson
Requires-Dist: ujson ; extra == 'ujson'
